flipflops/tff/t.v
module tff(t,clk,pre,clr,q,qbar);
input t,clk,pre,clr;
output q,qbar;
assign qbar = ~q;
reg q;

always@(posedge clk or posedge pre or posedge clr)
begin
    if(pre)
        q=1'b1;
    else if(clr)
        q=1'b0;
    else if(t)
        q=~q;
end
endmodule

module tff_tb;
reg t,clk,pre,clr;
wire q,qbar;
tff uut(t,clk,pre,clr,q,qbar);
initial begin
    clk=0;
    forever #5 clk=~clk;
end
initial begin
    $monitor($time," T=%b | Q=%b Qbar=%b",t,q,qbar);
    $dumpfile("tff_flipflop.vcd");
    $dumpvars(0,tff_tb);
    pre=1'b1;
    clr=1'b0; #10; // assign known values for T before pre is released
    pre=1'b0;
    #10 t=1'b1;
    #50 t=1'b0;
    #20 t=1'b1;
    #50 t=1'b1;
    #10
    $finish;
end
endmodule

flipflops/tff/tff_flipflop.vcd
$date
	Mon Oct 27 09:27:26 2025
$end
$version
	Icarus Verilog
$end
$timescale
	1s
$end
$scope module tff_tb $end
$var wire 1 ! qbar $end
$var wire 1 " q $end
$var reg 1 # clk $end
$var reg 1 $ clr $end
$var reg 1 % pre $end
$var reg 1 & t $end
$scope module uut $end
$var wire 1 # clk $end
$var wire 1 $ clr $end
$var wire 1 % pre $end
$var wire 1 ! qbar $end
$var wire 1 & t $end
$var reg 1 " q $end
$upscope $end
$upscope $end
$enddefinitions $end
$comment Show the parameter values. $end
$dumpall
$end
#0
$dumpvars
x&
1%
0$
0#
1"
0!
$end
#5
1#
#10
0#
0%
#15
1#
#20
0#
1&
#25
1!
0"
1#
#30
0#
#35
0!
1"
1#
#40
0#
#45
1!
0"
1#
#50
0#
#55
0!
1"
1#
#60
0#
#65
1!
0"
1#
#70
0#
0&
#75
1#
#80
0#
#85
1#
#90
0#
1&
#95
0!
1"
1#
#100
0#
#105
1!
0"
1#
#110
0#
#115
0!
1"
1#
#120
0#
#125
1!
0"
1#
#130
0#
#135
0!
1"
1#
#140
0#
#145
1!
0"
1#
