flipflops/sr/srff.v
module srff(clk,s,r,q,qbar);
input clk,s,r;
output q,qbar;
wire [1:0]w;


assign w[0]=~(s&clk);
assign w[1]=~(r&clk);
assign q=~(w[0]&qbar);
assign qbar=~(w[1]&q);

endmodule

module srff_test();
reg clk,s,r;
wire q,qbar;

srff f1 (.clk(clk),.s(s),.r(r),.q(q),.qbar(qbar));

initial clk = 1'b0;
always #5 clk = ~clk;

initial begin
    $monitor($time," s=%b, r=%b, q=%b, qbar=%b", s, r, q, qbar);
    $dumpfile("srff.vcd");
    $dumpvars(0,srff_test);
    s=0; r=1;
    #10 s=1; r=0;
    #10 s=0; r=0;
    #10 s=0; r=1;
    #10 s=1; r=1;
    #10 $finish;
end

endmodule

flipflops/sr/srff.vcd
$date
	Sun Oct 26 21:14:16 2025
$end
$version
	Icarus Verilog
$end
$timescale
	1s
$end
$scope module srff_test $end
$var wire 1 ! qbar $end
$var wire 1 " q $end
$var reg 1 # clk $end
$var reg 1 $ r $end
$var reg 1 % s $end
$scope module f1 $end
$var wire 1 # clk $end
$var wire 1 " q $end
$var wire 1 ! qbar $end
$var wire 1 $ r $end
$var wire 1 % s $end
$var wire 2 & w [1:0] $end
$upscope $end
$upscope $end
$enddefinitions $end
$comment Show the parameter values. $end
$dumpall
$end
#0
$dumpvars
b11 &
0%
1$
0#
x"
x!
$end
#5
0"
1!
b1 &
1#
#10
b11 &
0#
0$
1%
#15
0!
1"
b10 &
1#
#20
b11 &
0#
0%
#25
1#
#30
0#
1$
#35
0"
1!
b1 &
1#
#40
b11 &
0#
1%
#45
1"
b0 &
1#
