counters/johnson.v
module johnson(D,clk);
 output reg [0:3] D;
  input clk;

  initial begin
    D = 4'b0000; // Initialize the register to 0000
  end

  // On each positive edge of the clock, shift the bits according to the Johnson sequence.
  always @(posedge clk) begin
    D[3] <= D[2];
    D[2] <= D[1];
    D[1] <= D[0];
    D[0] <= ~D[3];
  end
endmodule

`timescale 1ns / 1ps

module tb;


  reg clk;
 
  wire[3:0]D;

johnson  uut (.clk(clk),.D(D));
  
  

  initial begin clk=0;  
  forever #5 clk=~clk; end

  always@(posedge clk)
   begin 
    $monitor($time,"%b%b%b%b",D[3],D[2],D[1],D[0]); 
    $dumpfile("johnson.vcd");
    $dumpvars(0,tb);
    #100 $finish;
    end
    
  

endmodule

counters/johnson.vcd
$date
	Sun Oct 26 23:36:51 2025
$end
$version
	Icarus Verilog
$end
$timescale
	1ps
$end
$scope module tb $end
$var wire 4 ! D [3:0] $end
$var reg 1 " clk $end
$scope module uut $end
$var wire 1 " clk $end
$var reg 4 # D [0:3] $end
$upscope $end
$upscope $end
$enddefinitions $end
$comment Show the parameter values. $end
$dumpall
$end
#5000
$dumpvars
b1000 #
1"
b1000 !
$end
#10000
0"
#15000
b1100 !
b1100 #
1"
#20000
0"
#25000
b1110 !
b1110 #
1"
#30000
0"
#35000
b1111 !
b1111 #
1"
#40000
0"
#45000
b111 !
b111 #
1"
#50000
0"
#55000
b11 !
b11 #
1"
#60000
0"
#65000
b1 !
b1 #
1"
#70000
0"
#75000
b0 !
b0 #
1"
#80000
0"
#85000
b1000 !
b1000 #
1"
#90000
0"
#95000
b1100 !
b1100 #
1"
#100000
0"
#105000
b1110 !
b1110 #
1"
