counters/ring.v
`timescale 1ns / 1ps
module ring_counter(clk, q);
  input clk;
  output reg [3:0] q;

  initial begin
    q = 4'b1000; // Initialize the counter to 0001
  end

  // On each positive edge of the clock, rotate the bits to the left
  always @(posedge clk) begin
    q <= {q[0],q[3:1]};
  end

endmodule

module tb;
  reg clk;
  wire [3:0] q;

  ring_counter uut (.clk(clk), .q(q));

  initial begin
    clk = 0;  
    forever #5 clk = ~clk; 
  end

  always @(posedge clk) begin 
    $monitor($time, "%b%b%b%b", q[3], q[2], q[1], q[0]); 
    $dumpfile("ring.vcd");
    $dumpvars(0, tb);
    #100 $finish;
  end
endmodule

counters/ring.vcd
$date
	Sun Oct 26 23:45:15 2025
$end
$version
	Icarus Verilog
$end
$timescale
	1ps
$end
$scope module tb $end
$var wire 4 ! q [3:0] $end
$var reg 1 " clk $end
$scope module uut $end
$var wire 1 " clk $end
$var reg 4 # q [3:0] $end
$upscope $end
$upscope $end
$enddefinitions $end
$comment Show the parameter values. $end
$dumpall
$end
#5000
$dumpvars
b100 #
1"
b100 !
$end
#10000
0"
#15000
b10 !
b10 #
1"
#20000
0"
#25000
b1 !
b1 #
1"
#30000
0"
#35000
b1000 !
b1000 #
1"
#40000
0"
#45000
b100 !
b100 #
1"
#50000
0"
#55000
b10 !
b10 #
1"
#60000
0"
#65000
b1 !
b1 #
1"
#70000
0"
#75000
b1000 !
b1000 #
1"
#80000
0"
#85000
b100 !
b100 #
1"
#90000
0"
#95000
b10 !
b10 #
1"
#100000
0"
#105000
b1 !
b1 #
1"
