counters/syn_up.v
module tff(t, clk, q, qbar, pre, clr);
    input t, clk, pre, clr;
    output q, qbar;
    reg q;                  // must be 'reg' because assigned inside always
    assign qbar = ~q;       // continuous assignment (combinational)

    always @(posedge clk or posedge pre or posedge clr)
    begin
        if (clr)
            q <= 1'b0;      // use non-blocking assignment
        else if (pre)
            q <= 1'b1;
        else if (t)
            q <= ~q;
    end
endmodule

module syn_up(t,clk,q,qbar,pre,clr);
input t,clk,pre,clr;
output [3:0] q;
output [3:0] qbar;
wire [3:0] q;
wire [3:0] qbar;

tff t0(1'b1,clk,q[0],qbar[0],pre,clr);
tff t1(q[0],clk,q[1],qbar[1],pre,clr);
tff t2(q[0]&q[1],clk,q[2],qbar[2],pre,clr);
tff t3(q[0]&q[1]&q[2],clk,q[3],qbar[3],pre,clr);
endmodule

module syn_uptb;
    reg clk, pre, clr;
    wire [3:0] q;
    wire [3:0] qbar;

    syn_up uut(.clk(clk), .q(q), .qbar(qbar), .pre(pre), .clr(clr));

    initial begin
        clk = 0;
        forever #5 clk = ~clk; // clock period = 10 time units
    end

    initial begin
        $monitor($time, " q=%b", q);
        $dumpfile("syn_up_counter.vcd");
        $dumpvars(0, syn_uptb);
        pre = 0; clr = 1;  // clear active
        #10 clr = 0; pre = 0;  // normal operation
        #200 $finish;
    end
endmodule

counters/syn_up_counter.vcd
$date
	Mon Oct 27 08:28:01 2025
$end
$version
	Icarus Verilog
$end
$timescale
	1s
$end
$scope module syn_uptb $end
$var wire 4 ! qbar [3:0] $end
$var wire 4 " q [3:0] $end
$var reg 1 # clk $end
$var reg 1 $ clr $end
$var reg 1 % pre $end
$scope module uut $end
$var wire 1 # clk $end
$var wire 1 $ clr $end
$var wire 1 % pre $end
$var wire 1 & t $end
$var wire 4 ' qbar [3:0] $end
$var wire 4 ( q [3:0] $end
$scope module t0 $end
$var wire 1 # clk $end
$var wire 1 $ clr $end
$var wire 1 % pre $end
$var wire 1 ) qbar $end
$var wire 1 * t $end
$var reg 1 + q $end
$upscope $end
$scope module t1 $end
$var wire 1 # clk $end
$var wire 1 $ clr $end
$var wire 1 % pre $end
$var wire 1 , qbar $end
$var wire 1 - t $end
$var reg 1 . q $end
$upscope $end
$scope module t2 $end
$var wire 1 # clk $end
$var wire 1 $ clr $end
$var wire 1 % pre $end
$var wire 1 / qbar $end
$var wire 1 0 t $end
$var reg 1 1 q $end
$upscope $end
$scope module t3 $end
$var wire 1 # clk $end
$var wire 1 $ clr $end
$var wire 1 % pre $end
$var wire 1 2 qbar $end
$var wire 1 3 t $end
$var reg 1 4 q $end
$upscope $end
$upscope $end
$upscope $end
$enddefinitions $end
$comment Show the parameter values. $end
$dumpall
$end
#0
$dumpvars
04
03
12
01
00
1/
0.
0-
1,
0+
1*
1)
b0 (
b1111 '
z&
0%
1$
0#
b0 "
b1111 !
$end
#5
1#
#10
0#
0$
#15
b1110 !
b1110 '
0)
1-
b1 "
b1 (
1+
1#
#20
0#
#25
0,
b1101 !
b1101 '
1)
0-
1.
b10 "
b10 (
0+
1#
#30
0#
#35
10
b1100 !
b1100 '
0)
1-
b11 "
b11 (
1+
1#
#40
0#
#45
00
0/
1,
b1011 !
b1011 '
1)
0-
11
0.
b100 "
b100 (
0+
1#
#50
0#
#55
b1010 !
b1010 '
0)
1-
b101 "
b101 (
1+
1#
#60
0#
#65
0,
b1001 !
b1001 '
1)
0-
1.
b110 "
b110 (
0+
1#
#70
0#
#75
13
10
b1000 !
b1000 '
0)
1-
b111 "
b111 (
1+
1#
#80
0#
#85
03
00
02
1/
1,
b111 !
b111 '
1)
0-
14
01
0.
b1000 "
b1000 (
0+
1#
#90
0#
#95
b110 !
b110 '
0)
1-
b1001 "
b1001 (
1+
1#
#100
0#
#105
0,
b101 !
b101 '
1)
0-
1.
b1010 "
b1010 (
0+
1#
#110
0#
#115
10
b100 !
b100 '
0)
1-
b1011 "
b1011 (
1+
1#
#120
0#
#125
00
0/
1,
b11 !
b11 '
1)
0-
11
0.
b1100 "
b1100 (
0+
1#
#130
0#
#135
b10 !
b10 '
0)
1-
b1101 "
b1101 (
1+
1#
#140
0#
#145
0,
b1 !
b1 '
1)
0-
1.
b1110 "
b1110 (
0+
1#
#150
0#
#155
13
10
b0 !
b0 '
0)
1-
b1111 "
b1111 (
1+
1#
#160
0#
#165
03
00
12
1/
1,
b1111 !
b1111 '
1)
0-
04
01
0.
b0 "
b0 (
0+
1#
#170
0#
#175
b1110 !
b1110 '
0)
1-
b1 "
b1 (
1+
1#
#180
0#
#185
0,
b1101 !
b1101 '
1)
0-
1.
b10 "
b10 (
0+
1#
#190
0#
#195
10
b1100 !
b1100 '
0)
1-
b11 "
b11 (
1+
1#
#200
0#
#205
00
0/
1,
b1011 !
b1011 '
1)
0-
11
0.
b100 "
b100 (
0+
1#
