adder/full.v
module full_adder(sum,cout,a,b,cin);
input a,b,cin;
output sum,cout;
wire w1,w2,w3;

xor x(sum,a,b,cin);
and a1(w1,a,b);
xor x2(w2,a,b);
and a2(w3,cin,w2);
or o(cout,w1,w3);

endmodule


module full_adder_sim();
reg a,b,cin;
wire sum,cout;

full_adder f(.a(a),.b(b),.cin(cin),.cout(cout),.sum(sum));
initial 
begin 
$monitor($time,"a=%b,b=%b,cin=%b,sum=%b,cout=%b",a,b,cin,sum,cout);
$dumpfile("full_adder.vcd");
$dumpvars(0,full_adder_sim);
#5 a=0;b=0;cin=0;
#5 cin=1;
#5 b=1;cin=0;
#5 cin=1;
#5 a=1;b=0;cin=0;
#5 cin=1;
#5 b=1;cin=0;
#5 cin=1;
#5 $finish;
end
endmodule

adder/full_adder.vcd
$date
	Mon Oct 27 09:16:17 2025
$end
$version
	Icarus Verilog
$end
$timescale
	1s
$end
$scope module full_adder_sim $end
$var wire 1 ! sum $end
$var wire 1 " cout $end
$var reg 1 # a $end
$var reg 1 $ b $end
$var reg 1 % cin $end
$scope module f $end
$var wire 1 # a $end
$var wire 1 $ b $end
$var wire 1 % cin $end
$var wire 1 " cout $end
$var wire 1 ! sum $end
$var wire 1 & w1 $end
$var wire 1 ' w2 $end
$var wire 1 ( w3 $end
$upscope $end
$upscope $end
$enddefinitions $end
$comment Show the parameter values. $end
$dumpall
$end
#0
$dumpvars
x(
x'
x&
x%
x$
x#
x"
x!
$end
#5
0"
0(
0!
0&
0'
0%
0$
0#
#10
1!
1%
#15
1'
0%
1$
#20
1"
0!
1(
1%
#25
0"
0(
1!
0%
0$
1#
#30
1"
0!
1(
1%
#35
0(
1&
0'
0%
1$
#40
1!
1%
