mux_8x1/mux_8x1.v
module MUX_8to1(A,B,C,D,E,F,G,H,S1,S2,S3,Y);
  // select lines
  input S1;
  input S2;
  input S3; // MSB
  
  // Data lines
  input A;
  input B;
  input C;
  input D;
  input E;
  input F;
  input G;
  input H;
  
  // Output line
  output Y;
  
  wire S1bar,S2bar,S3bar; // inverse of select lines
  
  wire R1,R2,R3,R4,R5,R6,R7,R8;  // output of first and gate level
  
  
  not notS1(S1bar,S1);
  not notS2(S2bar,S2);
  not notS3(S3bar,S3);
  
  
  
  and and1(R1,A,S3bar,S2bar,S1bar);
  and and2(R2,B,S3bar,S2bar,S1);
  and and3(R3,C,S3bar,S2,S1bar);
  and and4(R4,D,S3bar,S2,S1);
  and and5(R5,E,S3,S2bar,S1bar);
  and and6(R6,F,S3,S2bar,S1);
  and and7(R7,G,S3,S2,S1bar);
  and and8(R8,H,S3,S2,S1);
  
  or orlast(Y,R1,R2,R3,R4,R5,R6,R7,R8);
  
  
endmodule
  
  
  `timescale 1ns/1ps

module testbench;
  
  reg A,B,C,D,E,F,G,H;
  
  reg S1,S2,S3;
  
  wire Y;
  
  integer k;
  
  
  MUX_8to1 uut(.Y(Y),.A(A),.B(B),.C(C),.D(D),.E(E),.F(F),.G(G),.H(H),.S1(S1),.S2(S2),.S3(S3));
  
  initial 
    
    begin
      
      k=0;
      
      {H,G,F,E,D,C,B,A}=8'b11001010; // data for checking 
   
      {S3,S2,S1}=3'b0;
      
      
      for (k=0;k<=3'd7;k=k+1)
         
        begin
          
          
          {S3,S2,S1}=k[2:0];
          
          #5;
          
        end
      
      
      
    end
  
  initial 
    
    begin
      
      $monitor("time=%g\tA=%b\tB=%b\tC=%b\tD=%b\tE=%b\tF=%b\tG=%b\tH=%b\tS1=%b\tS2=%b\tS3=%b\tY=%b",$time,A,B,C,D,E,F,G,H,S1,S2,S3,Y);
     
      
    end
  
  initial 
    
    begin
      
    $dumpfile("waves.vcd"); 
      
    $dumpvars(0, testbench);
      
    end
  
  initial  begin #500; $finish; end
  
  
endmodule

mux_8x1/waves.vcd
$date
	Mon Oct 27 00:12:25 2025
$end
$version
	Icarus Verilog
$end
$timescale
	1ps
$end
$scope module testbench $end
$var wire 1 ! Y $end
$var reg 1 " A $end
$var reg 1 # B $end
$var reg 1 $ C $end
$var reg 1 % D $end
$var reg 1 & E $end
$var reg 1 ' F $end
$var reg 1 ( G $end
$var reg 1 ) H $end
$var reg 1 * S1 $end
$var reg 1 + S2 $end
$var reg 1 , S3 $end
$var integer 32 - k [31:0] $end
$scope module uut $end
$var wire 1 " A $end
$var wire 1 # B $end
$var wire 1 $ C $end
$var wire 1 % D $end
$var wire 1 & E $end
$var wire 1 ' F $end
$var wire 1 ( G $end
$var wire 1 ) H $end
$var wire 1 . R1 $end
$var wire 1 / R2 $end
$var wire 1 0 R3 $end
$var wire 1 1 R4 $end
$var wire 1 2 R5 $end
$var wire 1 3 R6 $end
$var wire 1 4 R7 $end
$var wire 1 5 R8 $end
$var wire 1 * S1 $end
$var wire 1 6 S1bar $end
$var wire 1 + S2 $end
$var wire 1 7 S2bar $end
$var wire 1 , S3 $end
$var wire 1 8 S3bar $end
$var wire 1 ! Y $end
$upscope $end
$upscope $end
$enddefinitions $end
$comment Show the parameter values. $end
$dumpall
$end
#0
$dumpvars
18
17
16
05
04
03
02
01
00
0/
0.
b0 -
0,
0+
0*
1)
1(
0'
0&
1%
0$
1#
0"
0!
$end
#5000
1!
06
1/
1*
b1 -
#10000
0!
07
16
0/
1+
0*
b10 -
#15000
1!
06
11
1*
b11 -
#20000
0!
08
17
16
01
1,
0+
0*
b100 -
#25000
06
1*
b101 -
#30000
1!
07
14
16
1+
0*
b110 -
#35000
04
06
15
1*
b111 -
#40000
b1000 -
