flipflop_gate/jk.v
`timescale 1ns / 1ps
module jk_flipflop (j,k,clk,pre,clr,q,qbar);
     input j,k,clk;
     input  clr,pre;
    output  q;
    output qbar;
    wire w1,w2;
    nand n1 (w1,j,clk,qbar);
    nand n2 (w2,k,clk,q);
    nand n3 (q,w1,qbar,pre);
    nand n4 (qbar,w2,q,clr);
endmodule

module jk_tb;
    reg j,k,clk;
    reg clr,pre;    
    wire q,qbar;
    jk_flipflop uut (j,k,clk,pre,clr,q,qbar);
    initial begin
        clk = 0;
        forever #5 clk = ~clk;
    end
    initial begin
    j = 0; k = 0; pre = 1; clr = 1;
end

    initial begin
        $monitor($time, " J=%b K=%b | Q=%b Qbar=%b", j, k, q, qbar);
        $dumpfile("jk_flipflop.vcd");
        $dumpvars(0,jk_tb);
        clr =1'b0;
        #10 clr=1'b1; pre=1'b1;
        #10 j = 1'b0; k = 1'b0;
                #10
        j = 1'b0; k = 1'b1; 
        #10
        j = 1'b1; k = 1'b0; 
        #10 
        j = 1'b1; k = 1'b1; 
        #10 
        j = 1'b0; k = 1'b0; 
        #1000
        $finish;
    end
endmodule

flipflop_gate/jk_flipflop.vcd
$date
	Mon Oct 27 00:33:56 2025
$end
$version
	Icarus Verilog
$end
$timescale
	1ps
$end
$scope module jk_tb $end
$var wire 1 ! qbar $end
$var wire 1 " q $end
$var reg 1 # clk $end
$var reg 1 $ clr $end
$var reg 1 % j $end
$var reg 1 & k $end
$var reg 1 ' pre $end
$scope module uut $end
$var wire 1 # clk $end
$var wire 1 $ clr $end
$var wire 1 % j $end
$var wire 1 & k $end
$var wire 1 ' pre $end
$var wire 1 " q $end
$var wire 1 ! qbar $end
$var wire 1 ( w1 $end
$var wire 1 ) w2 $end
$upscope $end
$upscope $end
$enddefinitions $end
$comment Show the parameter values. $end
$dumpall
$end
#0
$dumpvars
1)
1(
1'
0&
0%
0$
0#
0"
1!
$end
#5000
1#
#10000
0#
1$
#15000
1#
#20000
0#
#25000
1#
#30000
0#
1&
#35000
1#
#40000
0#
0&
1%
#45000
0!
1"
1(
1#
#50000
0#
1&
#55000
0(
1!
0)
1#
#60000
0"
1)
1(
0#
0&
0%
