flipflop_gate/jk_ms.v
`timescale 1ns / 1ps

module jkms(j,k,clk,pre,clr,q,qbar);
        input j,k,clk;
        input  clr,pre;
        output  q;
        output qbar;
        wire w1,w2,w3,w4,w5,w6;
        nand n1 (w1,j,clk,qbar);
        nand n2 (w2,k,clk,q);
        nand n3 (w3,w1,pre,w4);
        nand n4 (w4,w2,clr,w3);
        nand n5 (w5,w3,~clk);
        nand n6 (w6,w4,~clk);
        nand n7 (q,w5,qbar);
        nand n8 (qbar,w6,q);
endmodule
module jk_tb;
    reg j,k,clk;
    reg clr,pre;    
    wire q,qbar;
    jkms uut (j,k,clk,pre,clr,q,qbar);
    initial begin
        clk = 0;
        forever #5 clk = ~clk;
    end
    initial begin
    j = 0; k = 0; pre = 1; clr = 1;
end

    initial begin
        $monitor($time, " J=%b K=%b | Q=%b Qbar=%b", j, k, q, qbar);
        $dumpfile("jkms_flipflop.vcd");
        $dumpvars(0,jk_tb);
        pre=1'b1;
       clr=1'b0; j=1'b0;k=1'b0;#10; // assign known values for J and K before clr is released
       clr=1'b1;
        #10 j = 1'b0; k = 1'b0;
                #10
        j = 1'b0; k = 1'b1; 
        #10
        j = 1'b1; k = 1'b0; 
        #10 
        j = 1'b1; k = 1'b1; 
        #10 
        j = 1'b0; k = 1'b0; 
        #1000
        $finish;
    end
endmodule

flipflop_gate/jkms_flipflop.vcd
$date
	Mon Oct 27 00:41:36 2025
$end
$version
	Icarus Verilog
$end
$timescale
	1ps
$end
$scope module jk_tb $end
$var wire 1 ! qbar $end
$var wire 1 " q $end
$var reg 1 # clk $end
$var reg 1 $ clr $end
$var reg 1 % j $end
$var reg 1 & k $end
$var reg 1 ' pre $end
$scope module uut $end
$var wire 1 # clk $end
$var wire 1 $ clr $end
$var wire 1 % j $end
$var wire 1 & k $end
$var wire 1 ' pre $end
$var wire 1 " q $end
$var wire 1 ! qbar $end
$var wire 1 ( w1 $end
$var wire 1 ) w2 $end
$var wire 1 * w3 $end
$var wire 1 + w4 $end
$var wire 1 , w5 $end
$var wire 1 - w6 $end
$upscope $end
$upscope $end
$enddefinitions $end
$comment Show the parameter values. $end
$dumpall
$end
#0
$dumpvars
0-
1,
1+
0*
1)
1(
1'
0&
0%
0$
0#
0"
1!
$end
#5000
1-
1#
#10000
0-
0#
1$
#15000
1-
1#
#20000
0-
0#
#25000
1-
1#
#30000
0-
0#
1&
#35000
1-
1#
#40000
0-
0#
0&
1%
#45000
0+
1*
1-
0(
1#
#50000
0!
1"
0,
1(
0#
1&
#55000
0*
1+
1,
0)
1#
#60000
0"
1!
0-
1)
0#
0&
0%
#65000
1-
1#
#70000
0-
0#
#75000
1-
1#
#80000
0-
0#
#85000
1-
1#
#90000
0-
0#
#95000
1-
1#
#100000
0-
0#
#105000
1-
1#
#110000
0-
0#
#115000
1-
1#
#120000
0-
0#
#125000
1-
1#
#130000
0-
0#
#135000
1-
1#
#140000
0-
0#
#145000
1-
1#
#150000
0-
0#
#155000
1-
1#
#160000
0-
0#
#165000
1-
1#
#170000
0-
0#
#175000
1-
1#
#180000
0-
0#
#185000
1-
1#
#190000
0-
0#
#195000
1-
1#
#200000
0-
0#
#205000
1-
1#
#210000
0-
0#
#215000
1-
1#
#220000
0-
0#
#225000
1-
1#
#230000
0-
0#
#235000
1-
1#
#240000
0-
0#
#245000
1-
1#
#250000
0-
0#
#255000
1-
1#
#260000
0-
0#
#265000
1-
1#
#270000
0-
0#
#275000
1-
1#
#280000
0-
0#
#285000
1-
1#
#290000
0-
0#
#295000
1-
1#
#300000
0-
0#
#305000
1-
1#
#310000
0-
0#
#315000
1-
1#
#320000
0-
0#
#325000
1-
1#
#330000
0-
0#
#335000
1-
1#
#340000
0-
0#
#345000
1-
1#
#350000
0-
0#
#355000
1-
1#
#360000
0-
0#
#365000
1-
1#
#370000
0-
0#
#375000
1-
1#
#380000
0-
0#
#385000
1-
1#
#390000
0-
0#
#395000
1-
1#
#400000
0-
0#
#405000
1-
1#
#410000
0-
0#
#415000
1-
1#
#420000
0-
0#
#425000
1-
1#
#430000
0-
0#
#435000
1-
1#
#440000
0-
0#
#445000
1-
1#
#450000
0-
0#
#455000
1-
1#
#460000
0-
0#
#465000
1-
1#
#470000
0-
0#
#475000
1-
1#
#480000
0-
0#
#485000
1-
1#
#490000
0-
0#
#495000
1-
1#
#500000
0-
0#
#505000
1-
1#
#510000
0-
0#
#515000
1-
1#
#520000
0-
0#
#525000
1-
1#
#530000
0-
0#
#535000
1-
1#
#540000
0-
0#
#545000
1-
1#
#550000
0-
0#
#555000
1-
1#
#560000
0-
0#
#565000
1-
1#
#570000
0-
0#
#575000
1-
1#
#580000
0-
0#
#585000
1-
1#
#590000
0-
0#
#595000
1-
1#
#600000
0-
0#
#605000
1-
1#
#610000
0-
0#
#615000
1-
1#
#620000
0-
0#
#625000
1-
1#
#630000
0-
0#
#635000
1-
1#
#640000
0-
0#
#645000
1-
1#
#650000
0-
0#
#655000
1-
1#
#660000
0-
0#
#665000
1-
1#
#670000
0-
0#
#675000
1-
1#
#680000
0-
0#
#685000
1-
1#
#690000
0-
0#
#695000
1-
1#
#700000
0-
0#
#705000
1-
1#
#710000
0-
0#
#715000
1-
1#
#720000
0-
0#
#725000
1-
1#
#730000
0-
0#
#735000
1-
1#
#740000
0-
0#
#745000
1-
1#
#750000
0-
0#
#755000
1-
1#
#760000
0-
0#
#765000
1-
1#
#770000
0-
0#
#775000
1-
1#
#780000
0-
0#
#785000
1-
1#
#790000
0-
0#
#795000
1-
1#
#800000
0-
0#
#805000
1-
1#
#810000
0-
0#
#815000
1-
1#
#820000
0-
0#
#825000
1-
1#
#830000
0-
0#
#835000
1-
1#
#840000
0-
0#
#845000
1-
1#
#850000
0-
0#
#855000
1-
1#
#860000
0-
0#
#865000
1-
1#
#870000
0-
0#
#875000
1-
1#
#880000
0-
0#
#885000
1-
1#
#890000
0-
0#
#895000
1-
1#
#900000
0-
0#
#905000
1-
1#
#910000
0-
0#
#915000
1-
1#
#920000
0-
0#
#925000
1-
1#
#930000
0-
0#
#935000
1-
1#
#940000
0-
0#
#945000
1-
1#
#950000
0-
0#
#955000
1-
1#
#960000
0-
0#
#965000
1-
1#
#970000
0-
0#
#975000
1-
1#
#980000
0-
0#
#985000
1-
1#
#990000
0-
0#
#995000
1-
1#
#1000000
0-
0#
#1005000
1-
1#
#1010000
0-
0#
#1015000
1-
1#
#1020000
0-
0#
#1025000
1-
1#
#1030000
0-
0#
#1035000
1-
1#
#1040000
0-
0#
#1045000
1-
1#
#1050000
0-
0#
#1055000
1-
1#
#1060000
0-
0#
